{
  "hash": "3885af85",
  "configHash": "858a70d2",
  "lockfileHash": "b5d62ed9",
  "browserHash": "2c729364",
  "optimized": {
    "react": {
      "src": "../../node_modules/react/index.js",
      "file": "react.js",
      "fileHash": "c121aedc",
      "needsInterop": true
    },
    "react-dom/client": {
      "src": "../../node_modules/react-dom/client.js",
      "file": "react-dom_client.js",
      "fileHash": "721059b4",
      "needsInterop": true
    },
    "@aws-sdk/client-s3": {
      "src": "../../node_modules/@aws-sdk/client-s3/dist-es/index.js",
      "file": "@aws-sdk_client-s3.js",
      "fileHash": "255e58e2",
      "needsInterop": false
    },
    "@aws-sdk/client-sts": {
      "src": "../../node_modules/@aws-sdk/client-sts/dist-es/index.js",
      "file": "@aws-sdk_client-sts.js",
      "fileHash": "c9d0ab57",
      "needsInterop": false
    },
    "@aws-sdk/lib-storage": {
      "src": "../../node_modules/@aws-sdk/lib-storage/dist-es/index.js",
      "file": "@aws-sdk_lib-storage.js",
      "fileHash": "2d9605e5",
      "needsInterop": false
    },
    "@aws-sdk/s3-request-presigner": {
      "src": "../../node_modules/@aws-sdk/s3-request-presigner/dist-es/index.js",
      "file": "@aws-sdk_s3-request-presigner.js",
      "fileHash": "5f82e26b",
      "needsInterop": false
    },
    "framer-motion": {
      "src": "../../node_modules/framer-motion/dist/es/index.mjs",
      "file": "framer-motion.js",
      "fileHash": "9dff8828",
      "needsInterop": false
    },
    "hugeicons-react": {
      "src": "../../node_modules/hugeicons-react/dist/esm/hugeicons-react.js",
      "file": "hugeicons-react.js",
      "fileHash": "b8775b92",
      "needsInterop": false
    },
    "lucide-react": {
      "src": "../../node_modules/lucide-react/dist/esm/lucide-react.js",
      "file": "lucide-react.js",
      "fileHash": "53a99b92",
      "needsInterop": false
    }
  },
  "chunks": {
    "event-streams-VPTQXAU7": {
      "file": "event-streams-VPTQXAU7.js"
    },
    "bowser-TEF4JTIK": {
      "file": "bowser-TEF4JTIK.js"
    },
    "chunk-7PBECRR6": {
      "file": "chunk-7PBECRR6.js"
    },
    "chunk-2PXGS457": {
      "file": "chunk-2PXGS457.js"
    },
    "chunk-HQPYIJMI": {
      "file": "chunk-HQPYIJMI.js"
    },
    "chunk-SWHZIEQ7": {
      "file": "chunk-SWHZIEQ7.js"
    },
    "chunk-27CHP2CF": {
      "file": "chunk-27CHP2CF.js"
    },
    "chunk-ULSRCYB6": {
      "file": "chunk-ULSRCYB6.js"
    },
    "chunk-G3PMV62Z": {
      "file": "chunk-G3PMV62Z.js"
    }
  }
}